pyaqi/__init__.py
pyaqi/aqi_references.py
pyaqi-0.1.1.dist-info/LICENSE
pyaqi-0.1.1.dist-info/WHEEL
pyaqi-0.1.1.dist-info/METADATA
pyaqi-0.1.1.dist-info/RECORD
