Metadata-Version: 2.1
Name: pyaqi
Version: 0.1.1
Summary: Módulo para cálculo do Índice de Qualidade do Ar (IQAr).
Home-page: https://github.com/fernandascovino/iqarpy
License: MIT
Author: Fernanda Scovino
Author-email: fscovinom@gmail.com
Requires-Python: >=3.9,<4.0
Classifier: License :: OSI Approved :: MIT License
Classifier: Programming Language :: Python :: 3
Classifier: Programming Language :: Python :: 3.9
Classifier: Topic :: Software Development :: Libraries :: Python Modules
Project-URL: Repository, https://github.com/fernandascovino/iqarpy
